py_slack_notify/__init__.py
py_slack_notify/slack_notify.py
py3_slack_notify-0.4.2.dist-info/METADATA
py3_slack_notify-0.4.2.dist-info/WHEEL
py3_slack_notify-0.4.2.dist-info/top_level.txt
py3_slack_notify-0.4.2.dist-info/RECORD
